evbus_kafka/conf.py
evbus_kafka/version.py
evbus_kafka/acct/kafka/extras.py
evbus_kafka/acct/kafka/ssl.py
evbus_kafka/ingress/kakfa_queue.py
evbus_kafka-5.0.0.dist-info/LICENSE
evbus_kafka-5.0.0.dist-info/METADATA
evbus_kafka-5.0.0.dist-info/WHEEL
evbus_kafka-5.0.0.dist-info/top_level.txt
evbus_kafka-5.0.0.dist-info/RECORD
