Metadata-Version: 2.1
Name: evbus-kafka
Version: 5.0.0
Summary: evbus app-merge components for kafka queues
Home-page: https://gitlab.com/idem/evbus-kafka
Author: Joseph Hall
Author-email: perlhoser@gmail.com
License: UNKNOWN
Platform: UNKNOWN
Classifier: Environment :: Console
Classifier: Intended Audience :: Developers
Classifier: Intended Audience :: Information Technology
Classifier: Intended Audience :: System Administrators
Classifier: Operating System :: OS Independent
Classifier: Programming Language :: Python
Classifier: Programming Language :: Python :: 3.8
Classifier: Programming Language :: Python :: 3.9
Classifier: Programming Language :: Python :: 3.10
Classifier: Programming Language :: Python :: 3.11
Classifier: Development Status :: 5 - Production/Stable
Requires-Python: >=3.8
License-File: LICENSE
Requires-Dist: acct (>=6.5.1)
Requires-Dist: aiokafka
Requires-Dist: pop (>=21)
Requires-Dist: pop-evbus (>=6.1.1)
